{"AnimationType":{"GLUE_TRAP_CHARGING_ALERTED":315,"PUNCH":5,"SWORD_SWING_3":4,"WINTER_BOSS_DEATH":354,"PINATA_HIT_2":227,"ELK_CHARGING":184,"BEAR_CLAWS_SWIPE":160,"FP_HANDS_RUNNING_HEAD":310,"CHEERS_BOTTLE":395,"GREAT_HAMMER_CHARGED_SWING":432,"PISTOL_IDLE":139,"KNIFE_1":336,"SCYTHE_SLASH_1_FP":423,"ROBLOX_DEFAULT_FREEFALL":337,"VOID_TRANQUILITY":727,"AXOLOTL_SWIM":61,"FP_HOLD":11,"TURTLE_IDLE":635,"DIAMOND_GUARDIAN_ATTACK_2":384,"TARGET_DUMMY_RANGED_ATTACK":546,"SLOW_CLAP":396,"CARD_THROW":458,"PINATA_FEED":228,"VOID_DRAGON_IDLE":262,"DRAGON_SWORD_ULT_FP":558,"GOLDEN_GOOSE_SCARED":495,"MERCHANT_CURTAIN_OPEN":405,"CHICKEN_RUN":460,"SKELETON_SPAWN":273,"ANGEL_WINGS_PLAYER_FLYING":792,"KNEEL_DOWN":617,"DROPPED_THIS_KING":608,"PARTY_UP":145,"KEEPER_SPAWN":277,"GOLEM_BOSS_HAMMER_SLAM":390,"GRIM_REAPER_DEAD_TO_ME_EMOTE":624,"GOLDEN_GOOSE_LAY_EGG":494,"HEAVENLY_SWORD_SWING":168,"VOID_DRAGON_FLYING":264,"ROCK_PAPER_SCISSORS":187,"ROBLOX_SHRUG":753,"CRAB_BOSS_WALK":484,"REPAIR_ENCHANT_TABLE":88,"BHAA_MOVEMENT":781,"WINTER_BOSS_SLAM_AXE":357,"WIZARD_LIGHTNING_CAST":25,"SWORD_IDLE":0,"HARPOON_RETURN":625,"CRAB_BOSS_DIG_UP":481,"GLUE_TRAP_IDLE":312,"PENGUIN_KILL_EFFECT_3":539,"STAR_ITEM_CONSUME":191,"FP_HANNAH_ATTACK":244,"LARGE_FALL_2":306,"SCARAB_ATTACK_2":800,"GHOST_IDLE":79,"SCYTHE_PULL_1":427,"VOID_CRAB_FALLING":199,"PISTOL_SHOOT":138,"TARGET_DUMMY_DAMAGED":541,"PIRATES_GOODBYE":239,"DART_THROW_2":826,"FP_CROSSBOW_AIM":16,"PALADIN_LAND":275,"STAR_RANDOM_SPIN":190,"FP_CARROT_CANNON_IDLE":143,"PENGUIN_JUMP_2":209,"HALLOWEEN_BOSS_CAST":289,"WIZARD_BALL_CAST":26,"WARLOCK_IDLE":503,"SPIRIT_HEAL_ALT":720,"JUGGERNAUT_ATTACK_3_FP":331,"ENCHANT_TABLE_GLITCHED_IDLE":248,"MINER_MINE_STONE":133,"PLAYER_VACUUM_SUCK":173,"SEAHORSE_SWIM_LOOP":369,"HARPOON_ATTACK_START":629,"VOID_CRAB_IDLE":200,"FALCON_ATTACK":595,"THIRSTY_EMOTE":765,"FALCON_SOAR":592,"SKELETON_WALK":269,"CROSSBOW_AIM":131,"VOID_HUNTER_WOLF_BITE":746,"CACTUS_SPIT":755,"SHIELD_SWORD_IDLE":473,"WINTER_BOSS_RUN":361,"CRAB_HEAD_SCRATCH":645,"FP_INFERNO_SWORD_SPIN":170,"ANGEL_WINGS_WINGS_IDLE":612,"RAPIER_THRUST_1":564,"SCYTHE_SLASH_2_FP":424,"TARGET_DUMMY_ALERT":543,"BEACH_VACATION":188,"CURSED_COFFIN_RESPAWN":498,"ASCEND":42,"NEW_SWORD_CHARGE":770,"EGYPTIAN_CAT_WALK":760,"OIL_SPIT":85,"BOOK_READ":266,"JUGGERNAUT_LEAP_FP":324,"BHAA_SUMMON":778,"ROCK_OUT":144,"TENNIS_RACKET_IDLE":234,"SCYTHE_SLASH":95,"BOBA_BLASTER_FIRE":153,"HANNAH_ATTACK":243,"WIZARD_ABILITY_SWITCH":27,"GAUNTLETS_CHARGE_SUPER_PUNCH":443,"VACUUM_STARTUP":56,"GRAVEYARD_DIG":283,"PLACE_BLOCK":622,"INFERNAL_SHIELD_CHARGE":401,"JUGGERNAUT_ATTACK_1_FP":329,"WINTER_BOSS_SPAWN":359,"JELLY_SQUISH":90,"OWL_GRAB":373,"CRAB_BOSS_STAB_50":485,"FP_JAILOR_IMPRISON":343,"GLUE_TRAP_CHARGING":314,"GLUE_TRAP_FLYING":311,"PINATA_IDLE_3":225,"USE_CROSS":276,"ZEN_HOVER":268,"FISHING_ROD_PULLING":75,"FLYING_CLOUD_IDLE":415,"EATING_POPCORN":512,"WINTER_BOSS_IDLE":355,"SCYTHE_SLASH_2":422,"CRAB_BOSS_FLIP_GROUND":482,"GAUNTLETS_IDLE":444,"HOVER_BOARD_IDLE":300,"SIT_FLAT":767,"TALL_PENGUIN_WALK":103,"FLAMETHROWER_USE":31,"JUGGERNAUT_ATTACK_1":326,"SKATING_SLOW":741,"ANGEL_WINGS_PLAYER_FLY":614,"SCYTHE_SPIN":425,"FROSTY_HAMMER_1":347,"FP_HANDS_RUNNING":304,"JUGGERNAUT_SPIN":319,"VOID_HUNTER_WOLF_IDLE":745,"GOODNIGHT_DANCE":654,"ROBLOX_GHOST_RUN":717,"FP_SPEAR_STAB":675,"HEADHUNTER_SHOOT_FP":410,"FP_TWIRLBLADE_ATTACK_SPIN":127,"FROSTY_HAMMER_3_FP":352,"SNAP_TRAP_CLOSE":71,"CHICKEN_JUMP":463,"SUMMONER_DRAGON_ATTACK":649,"NET_CATCH":37,"FP_SLEDGEHAMMER_SWING":334,"SUMMON_SNOW":536,"DAGGER_SWING_2":418,"DUCK_HONK":119,"PAINT_SHOTGUN_SHOOT":134,"HEADHUNTER_AIM":411,"HALLOWEEN_RAVEN_IDLE_LOOP":286,"GAUNTLETS_IDLE_1ST":451,"ELK_WALKING":180,"ELK_FALLING":181,"VOID_MEDITATION_KNEEL":728,"FP_HANDS_RUNNING_RIGHT_ARM":309,"DODO_BIRD_WALK":44,"SPIDER_QUEEN_IDLE_AGGRO":705,"SPIDER_BOSS_SPIN":680,"VOID_DRAGON_BREATH_FIRE":261,"FP_EQUIP":13,"ANGEL_WINGS_DIVE":791,"DRAGON_DANCE":821,"DODO_BIRD_SQUAWK":48,"RAVEN_SPAWN":34,"BUILDER_HAMMER_HIT":6,"FP_SWING_SWORD":15,"WARLOCK_CHARGE_UP":506,"DAGGER_SLASH":230,"AXOLOTL_EASTER_ABILITY":69,"USE_GRAVESTONE":272,"FP_HEAVENLY_SWORD_SWING":169,"ENCHANT_TABLE_LOOP":91,"SPIRIT_ASSASSIN_KILL_EFFECT_GHOST_2":574,"NINJA_RUN":531,"HALLOWEEN_RAVEN_FLIGHT_LOOP":287,"TINKER_FALL":603,"DUCK_ATTACK":117,"YAWN":813,"SAW_ATTACK_2":399,"FROSTY_HAMMER_2_FP":351,"TARGET_DUMMY_DEATH":542,"ROCKET_LAUNCHER_RELOAD":52,"WIGGLE":186,"LUCKY_BOX_OPEN":370,"AXOLOTL_EASTER_SWIM":68,"TINKER_ATTACK":599,"BIG_PENGUIN_WALK":107,"DRAGON_SLAYER_PUNCH":253,"FP_WALK":19,"LASSO_CHARGE":22,"BOW_DRAW":130,"RAVEN_HOLD":38,"CHARGED_HAMMER_SWING":335,"JUGGERNAUT_SPIN_FP":325,"TALL_PENGUIN_JUMP":104,"CARROT_CANNON_IDLE":141,"CLASSIC_PENGUIN_WALK":214,"ROCKET_LAUNCHER_SHOT":51,"SHEEP_IDLE":149,"GOLD_FISH_SWIM":671,"GRAVEYARD_JUMP":284,"TRAPPER_SLASH":72,"OWL_SHOOT":372,"SPIDER_IDLE":502,"SPIRIT_ASSASSIN_SPIN_EMOTE":571,"HARPOON_VICTIM_STUN":626,"HALLOWEEN_ALTAR_LOOP":297,"ATTACK_SPIRIT_ATTACK":721,"SWORD_SWING_2":3,"CRAB_BOSS_DEATH":479,"TRIUMPH_STATUE_3":661,"SPEAR_IDLE":82,"COMET_VOLLEY_SHOOTING_TO_FALLING_TRANSITION":552,"TAME_SHEEP":150,"HALLOWEEN_RAVEN_FLIGHT":288,"FALCON_DIVE":594,"GUN_BLADE_IDLE":809,"NEW_SWORD_CHARGE_FP":772,"CRAB_BOSS_STAB_130":487,"FALCON_RECOIL":596,"SIDE_TO_SIDE":146,"HALLOWEEN_BOSS_WAVE":295,"CLASSIC_PENGUIN_SMALL_ATTACK":217,"PINATA_IDLE_2":224,"DRAGON_SWORD_FIRE":559,"SHEEP_JUMP":148,"PAN_SWING":156,"SHEEP_WALK":147,"CHICKEN_FLAP":464,"HOLDING_SIGN":824,"CARROT_CANNON_SHOOT":140,"HALLOWEEN_ALTAR_SKULL_ROTATE":296,"PINATA_HIT_1":226,"CRAB_BOSS_BARRAGE_ATTACK":477,"CENTIPEDE_BED_BREAK":829,"SPIDER_QUEEN_LANDING":706,"HEADS_OFF":827,"KEEPER_ATTACK_2":281,"DEFAULT_SPIDER_LOOKING":685,"VOID_HOUND_ATTACK_4":733,"AXOLOTL_ABILITY":62,"TURTLE_DANCE":640,"FP_DAGGER_SLASH":232,"SHOVEL_DIG":164,"DRAGON_WALK":820,"CRAB_IDLE":641,"CHAMELEON_WALK":818,"DRAGON_SLAYER_LAUNCH_IMPACT":255,"CHAMELEON_IDLE":817,"SPIRIT_OWL_EMOTE_OWL":816,"SPIRIT_OWL_EMOTE_CHARACTER":815,"WINTER_BOSS_DASH_ATTACK":353,"BEAR_CLAWS_FLURRY":161,"DISMANTLE_KILL_EFFECT_UPPER":651,"KNIGHT_SHIELD_RAISE_SHIELD":709,"FUNKY_DANCE":655,"PICKAXE_SWORD":679,"FP_CARROT_CANNON_SHOOT":142,"PILLOW_FIGHT":812,"PILLOW_SWING":811,"SWORD_SWING":1,"USE_TABLET":28,"WALK_LIKE_EGYPTIAN":774,"LARGE_FALL_3":307,"GREAT_HAMMER_SWING_2":431,"GOLDEN_GOOSE_IDLE":493,"HOVER_BOARD_JUMP":299,"OWL_FLY_STEADY_HEIGHT":375,"GUN_BLADE_RUN":810,"SPIRIT_GARDENER_WATER":681,"SHIELD_SWORD_WALKING":472,"SHARK_BITE":807,"NORMAL_PENGUIN_IDLE":98,"EQUIP_3":10,"WATER_GUN_SHOOT":806,"WATER_GUN_IDLE":805,"FIRE_SHEEP_ATTACK":378,"BEACH_VOLLEY_BALL_BALL":804,"BEACH_VOLLEY_BALL_R15_CHARACTER":803,"VOID_DRAGON_BREATH_CHARGE":260,"VOID_PORTAL_IDLE":204,"PIRATE_TREASURE_EMOTE_LOOPED":802,"DINO_IDLE":179,"PIRATE_TREASURE_EMOTE_SITTING":801,"LASER_SWORD_SWING_3RD_PERSON_2":338,"CRAB_BOSS_IDLE":476,"DRAGON_BREATH":251,"SCARAB_ATTACK_1":799,"HALLOWEEN_BOSS_IDLE":292,"TOURNAMENT_WINNER":678,"HALLOWEEN_BOSS_SUMMON":294,"SCARAB_WALK":798,"SCARAB_FLY":797,"THROW_CHICKEN":465,"VOID_CRAB_RIGHT_ATTACK":195,"ANGEL_WINGS_PLAYER_GROUND_SMASH":796,"ANGEL_WINGS_GROUND_SMASH":795,"KNIGHTS_BOW":267,"ANGEL_WINGS_PLAYER_DIVE":794,"VOID_HOUND_IDLE":735,"DIAMOND_GUARDIAN_DEATH":385,"HARPOON_HANG_IDLE":628,"ANGEL_WINGS_FLYING":789,"MERCHANT_WAGON_IDLE":406,"CRAB_BOSS_STAB_90":486,"GREAT_HAMMER_SWING_2_FP":435,"RAIN_DANCE":788,"SKORP_MOVE":787,"ELK_IDLE":183,"GATHER_BOT_WALK_CARRY_ITEM":517,"SKORP_ATTACK":785,"BHAA_ROCKSPIKE":784,"BHAA_IDLE":783,"ENCHANT_TABLE_GLITCHED_ACTION":247,"BHAA_DEATH":782,"BHAA_SPAWN":780,"BHAA_ROCKWAVE":779,"GAUNTLETS_SUPER_PUNCH_1ST":449,"SPIRIT_ASSASSIN_AD":159,"BHAA_ATTACK":777,"HALLOWEEN_BOSS_SPAWN":293,"CHICKEN_IDLE":461,"SNIPER_PENGUIN_SHOOT_2":210,"FROSTY_HAMMER_UPGRADE":345,"NEW_SWORD_SWING":771,"VACUUM_SUCK":55,"CRAB_BOSS_SPAWN":483,"DUST_DEVIL_SPIN":769,"YETI_ROAR":89,"DAGGER_SWING_1":417,"CRAB_BOSS_DIG_DOWN":480,"CACTUS_CAST":756,"FLYING_CARPET_IDLE":766,"CAUGHT_IN_4K":513,"TWIRLBLADE_ATTACK_2":122,"FROSTY_HAMMER_SLAM":344,"FP_PAINT_SHOTGUN_SHOOT":136,"HOLD_CHICKEN":466,"CRAB_BOSS_STAB_270":489,"CRAB_HEAD_SWAY":644,"ROBLOX_DEFAULT_IDLE":692,"PENGUIN_ATTACK_2":206,"TINKER_PLACE_BLOCK":605,"TINKER_JUMP":602,"VOID_CRAB_WALKING":203,"TWIRLBLADE_ATTACK_IDLE":124,"EGYPTIAN_CAT_IDLE":759,"VOID_DRAGON_WING_TRANSFORM":258,"AIRBENDER_CAST":758,"DINO_FALLING":175,"BUNNY_SIDE_TO_SIDE":754,"ROBLOX_LOCOMOTION_ASTRONAUT_FALL":752,"ROBLOX_NINJA_JUMP":751,"ANUBIS_ATTACK":776,"FISHING_ROD_CAST":73,"FRONT_FLIP":749,"HOVERBOARD_IDLE":748,"HOVERBOARD_MOVEMENT":747,"PINATA_IDLE_1":223,"SKATING_FAST":743,"SKATING_MEDIUIM":742,"WARRIOR_SPIDER_ATTACK_2":696,"SKATING_BUNNY_HOP":739,"RIFT_REVIVE":285,"MARSHMALLOW_ROAST_ACTION":738,"SCYTHE_PULL":93,"MARSHMALLOW_ROAST_LOOP":737,"VOID_DRAGON_TRANSFORM":265,"DODO_BIRD_FLUTTER":47,"DINO_WALKING":174,"VOID_HOUND_ATTACK_1":730,"FORGE":416,"SCISSOR_SWORD_SWING_1":569,"VOID_HOUND_WALK":734,"GAUNTLETS_UPPERCUT":441,"VACUUM_IDLE":57,"SPEAR_STARTUP":83,"DRAGON_FLYING":250,"DRAGON_HEAD_SWAY":823,"VOID_HOUND_ATTACK_3":732,"SPIDER_WEBBED":499,"VOID_HOUND_ATTACK_2":731,"VOID_MEDITATION_IDLE":729,"GLUE_TRAP_JUMP":313,"DUCK_WALK_EMOTE":726,"ANGEL_WINGS_PLAYER_DIVING_IDLE":793,"WIZARD_LIGHTNING_STRIKE_CAST":404,"JUGGERNAUT_GROUND_STAB_FP":323,"SPIDER_QUEEN_WEB_SPRAY":707,"RABBIT_HAT_TRICK":724,"HEAL_SPIRIT_ATTACK_ALT":723,"FROSTY_HAMMER_2":348,"GOLDEN_SNAKE_WALK":688,"LUXURY_CHAIR":453,"AXOLOTL_SPIN":63,"DIAMOND_GUARDIAN_MOVE":382,"SPIRIT_HEAL":719,"JELLYFISH_ATTACK":632,"KEEPER_IDLE":278,"DIAMOND_GUARDIAN_IDLE":381,"GAUNTLETS_JAB":438,"JELLYFISH_SPAWN":633,"ROBLOX_GHOST_FLOATING":715,"OIL_EAT":84,"CLASSIC_WIZARD_PENGUIN_IDLE":221,"FP_TWIRLBLADE_ATTACK_2":126,"HALLOWEEN_WREN_COFFIN_OPEN_CLOSE":714,"CHARGE_SHIELD_CHARGE":50,"JADE_HAMMER_IDLE":39,"TWIRLBLADE_ATTACK_SPIN":123,"KNIGHT_SHIELD_THIRD_PERSON_BASH":713,"KNIGHT_SHIELD_FP_BASH":712,"BIG_PENGUIN_JUMP":108,"KNIGHT_SHIELD_FP_DEFEND":711,"EQUIP_1":8,"KNIGHT_SHIELD_FP_GUARD_DOWN":710,"SCYTHE_SLASH_1":421,"JUGGERNAUT_ATTACK_3":328,"SUMMONER_CLAW_ATTACK":650,"THRILLER":828,"NINJA_THROW_CHAKRAM_RIGHT":532,"SPIDER_QUEEN_IDLE":704,"JUGGERNAUT_PULL_SWORD":317,"GAUNTLETS_CROSS":439,"TENNIS_RACKET_HIT":233,"BIG_PENGUIN_ATTACK":105,"NORMAL_PENGUIN_ATTACK":97,"GREAT_HAMMER_CHARGED_SWING_FP":436,"SPIDER_GUARD_SHOOT":698,"PARTY_POPPER_HOLD":364,"SPIDER_QUEEN_WEB_CAST_SKY":702,"STATUE":41,"EGYPTIAN_CAT_HEAD_SCRATCH":763,"FISHING_ROD_CATCH_SUCCESS":77,"SPIDER_GUARD_DEATH":700,"RAVEN_THROW":35,"SPIDER_GUARD_PULL":699,"DRAGON_BLINK":822,"WINTER_BOSS_SLAM_FRONT":358,"SKATING_WALK":740,"RAVEN_ATTACK_KILL_EFFECT":657,"MINING_FP":694,"MINING":693,"BLASTING_OFF_AGAIN_0":587,"ROBLOX_DEFAULT_WALK":691,"RAVEN_LOOP":33,"GOLDEN_SNAKE_DANCE":690,"REPAIR_SNOW_CONE_MACHINE":235,"LASER_SWORD_SWING_3RD_PERSON_1":339,"GOLDEN_SNAKE_IDLE":689,"HEAL_SPIRIT_ATTACK":722,"SPEAR_CHARGE_1":672,"DEFAULT_SPIDER_IDLE":687,"AXOLOTL_EASTER_IDLE":67,"GOLEM_BOSS_FIST_SLAM":391,"SKELETON_IDLE":270,"DEFAULT_SPIDER_SCRATCHING":686,"SILLY_LEGS_DANCE":610,"FP_HANDS_IDLE":303,"VACUUM_LAUNCH":59,"DEFAULT_SPIDER_DANCE":683,"DEFAULT_SPIDER_WALK":682,"EAT":7,"GUN_BLADE_FIRE":808,"ELEKTRA_TP":814,"KICK_1":526,"SPRING_PUNCH_ATTACK":677,"TORNADO_LAUNCHER_HOLD":154,"SLIME_TAMER_FLUTE_USE":523,"POGO_STICK_MOUNT":676,"FP_USE_ITEM":14,"FP_SPEAR_CHARGE":674,"VOID_DRAGON_RUNNING":263,"GOLEM_BOSS_SPAWN":386,"INFERNAL_SHIELD_LEAP":402,"FISHING_ROD_CATCH_FAIL":76,"STAR_IDLE":189,"ROCKET_LAUNCHER_IDLE":53,"REBELLION_FORWARD":669,"REBELLION_POINT_SWORD":668,"FACE_PALM":452,"HALLOWEEN_BOSS_DEATH":291,"SORCERER_SPELL_CHARGE":556,"TURTLE_HEAD_SCRATCH":639,"BLASTING_OFF_AGAIN_4":591,"RAPIER_THRUST_2":565,"WARLOCK_FORWARD_CAST":505,"TRIUMPH_STATUE_3_FRAME":665,"TRIUMPH_STATUE_2_FRAME":664,"GAUNTLETS_CROSS_1ST":446,"TRIUMPH_STATUE_1_FRAME":663,"GHOST_FLIP":78,"SAW_ATTACK":398,"NIGHTMARE_LOOP":151,"TRIUMPH_STATUE_4":662,"TRIUMPH_STATUE_2":660,"COMET_VOLLEY_TARGETING_IDLE":553,"CLASSIC_WIZARD_PENGUIN_ATTACK":222,"CRAB_BOSS_STAB_310":490,"CLASSIC_PENGUIN_IDLE":215,"PENGUIN_FALL":212,"SWORD_SWING_1":2,"DAGGER_SWING_FP":420,"ALCHEMY_CIRCLE_KILL_EFFECT":658,"WARRIOR_SPIDER_ATTACK_1":695,"SWORD_TWIRL":656,"GRIDDY":653,"DISMANTLE_KILL_EFFECT_LOWER":652,"SPIDER_QUEEN_DEATH":708,"CRAB_DANCE_EMOTE":648,"ICY_DELIGHT":647,"LASER_SWORD_SWING_1":340,"EGYPTIAN_CAT_HEAD_SWAY":762,"COMET_VOLLEY_ASCEND":550,"FP_INFERNO_SWORD_CHARGE":171,"DINO_HIT":177,"SEAHORSE_IDLE_LOOP":366,"DRAGON_IDLE":819,"SPITTER_SPIT":697,"WINTER_BOSS_RAISE_AXE":356,"JUGGERNAUT_ATTACK_2":327,"COMET_VOLLEY_FALLING":551,"MERCHANT_IDLE":407,"TURTLE_HEAD_SWAY":638,"VOID_CRAB_JUMP":193,"TURTLE_WALK":636,"SIT_ON_DODO_BIRD":49,"DRILL_SPIN_LOOP":400,"JELLYFISH_MOUNT_IDLE":634,"ROBLOX_GHOST_WALK":716,"SPIRIT_FLOATING_IDLE":718,"ELEKTRA_DASH":619,"GOLDEN_GOOSE_GLIDE":492,"HARPOON_STTACK":630,"CLASSIC_TNT_PENGUIN_ATTACK":219,"ANGEL_WINGS_DIVING_IDLE":790,"DIAMOND_GUARDIAN_ATTACK_1":383,"HARPOON_HANG":627,"MIRROR_KILL_EFFECT":246,"DAGGER_CHARGE":229,"FLOAT_AWAY_LOOP":621,"FLOAT_AWAY_HIT":620,"GAUNTLETS_UPPERCUT_1ST":448,"JELLYFISH_IDLE":631,"KNEEL_IDLE":618,"DRAGON_SWIRL":563,"GOLEM_BOSS_HAMMER_RAISE":389,"PALADIN_JUMP":274,"CONGA_DANCE":615,"SLEDGEHAMMER_SWING":333,"EASTER_BUNNY_EMOTE_BUNNY":163,"ANGEL_WINGS_PLAYER_IDLE":613,"HEAVEN_ASCEND":611,"DROPPED_THIS_KING_LONG":609,"JUGGERNAUT_ATTACK_2_FP":330,"PUSH_UP_GLASSES":607,"TINKER_HEAVY_ATTACK":606,"TINKER_BREAK_BLOCK":604,"TINKER_AIM":601,"TINKER_IDLE":600,"LARGE_FALL_1":305,"GATHER_BOT_IDLE":518,"MENDING_CANOPY_CHARGE":597,"CLASSIC_SNIPER_PENGUIN_ATTACK":218,"BARBARIAN_RAGEBLADE_MASTER":471,"FALCON_WING_FLAP":593,"WEREWOLF_HOWL":510,"BLASTING_OFF_AGAIN_2":589,"BLASTING_OFF_AGAIN_1":588,"DAO_CHARGE":113,"GRENADE_THROW":54,"TALL_PENGUIN_ATTACK":101,"CAPTAIN_PENGUIN_ATTACK":110,"DRAGON_MORTAR_GET_UP":578,"GAUNTLETS_CHARGE_SUPER_PUNCH_1ST":450,"EGG_HUNT_GOLDEN_GOOSE_DANCE":585,"MAP_TROPHY_HOLD":584,"MAP_TROPHY_THROW":583,"DRAGON_KILL_EFFECT":582,"NINJA_THROW_CHAKRAM_LEFT":533,"DODO_BIRD_FALL":46,"CELEBRATION":581,"KEEPER_ATTACK":280,"PAINT_SHOTGUN_IDLE":135,"DRAGON_MORTAR_FIRE":579,"FP_DAGGER_CHARGE":231,"GUITAR_HEAL":21,"DRAGON_MORTAR_SETUP":577,"COIN_TOSS":245,"AXOLOTL_REINDEER_SWIM":65,"R15_ANIM_EMOTE_SLEEP":750,"HEADHUNTER_SHOOT":409,"SPIRIT_ASSASSIN_KILL_EFFECT_GHOST_3":575,"SPIRIT_ASSASSIN_KILL_EFFECT_GHOST_1":573,"SPIRIT_ASSASSIN_KILL_EFFECT_PLAYER":572,"FLAMETHROWER_IDLE":30,"BOW_FIRE":129,"TORNADO_LAUNCHER_SHOOT":155,"WAND_CAST":567,"WAND_IDLE":566,"KNEEL_UP":616,"QUEEN_BEE_FLOAT":397,"FORGE_CRYSTAL_GROW":459,"DRAGON_SWORD_ULT":557,"TRAIN_ENGINE_LOOP":547,"OWL_INTERACTION":377,"GAUNTLETS_HOOK":440,"JAILOR_IMPRISON":342,"HANG_GLIDER_BODY":86,"WARLOCK_ENTER_SCENE":507,"DRAGON_SWORD_FIRE_FP":560,"BEE_FLAP":36,"VOID_CRAB_CLEANING":201,"DRAGON_SMASH_1":561,"SEARCHING_FAR_AWAY":238,"FROSTY_HAMMER_1_FP":350,"TRIUMPH_STATUE_4_FRAME":666,"WIND_TUNNEL_FLYING":555,"SCYTHE_SPIN_FP":426,"DISCO_DANCE":394,"HANNAH_JUMP_DOWN":240,"TRAIN_COAL_CABIN_LOOP":548,"DAVEY_JUMP_DOWN":241,"SCYTHE_SWING":94,"SKATING_SPIN_JUMP":744,"CROSSBOW_FIRE":132,"NORMAL_PENGUIN_WALK":99,"VOID_CRAB_MIDDLE_ATTACK":202,"FORK_TRIDENT_IDLE":470,"TARGET_DUMMY_SOLO_ATTACK":544,"TARGET_DUMMY_SPAWN":540,"TWIRLBLADE_ATTACK_1":121,"PENGUIN_KILL_EFFECT_2":538,"PENGUIN_KILL_EFFECT_1":537,"BOOMERANG_THROW":535,"WINTER_BOSS_SPIN_AXE":363,"NECROMANCER_SUMMON":271,"KICK_4":529,"KICK_3":528,"KICKER_STOMP":525,"KICK_2":527,"HALLOWEEN_BOSS_CAST_BEAM":290,"DUCK_JUMP":118,"SLIME_TAMER_FLUTE_USE_FP":524,"SLIME_MOVEMENT":522,"ELK_JUMP":182,"SLIME_JUMP":521,"GOLDEN_GOOSE_WALKING":497,"STEAM_ENGINEER_OVERCLOCK":519,"JUGGERNAUT_STAB_GROUND":320,"TINKER_RUN":598,"SNIPER_PENGUIN_WALKING_2":211,"GATHER_BOT_WALK":516,"GATHER_BOT_CONSTRUCTION":515,"DART_THROW_1":825,"EGYPTIAN_CAT_DANCE":764,"STURDY":511,"BLASTING_OFF_AGAIN_3":590,"WEREWOLF_CHARGE":509,"GRIM_REAPER_CONSUME":24,"INFERNO_SWORD_SPIN":166,"FP_SHIELD_USE":18,"ENVELOPE_THROW":580,"TURN_AROUND":508,"WINTER_BOSS_THROW":362,"FLAMETHROWER_UPGRADE":32,"TRAIN_PASSANGER_CABIN_LOOP":549,"GOLDEN_GOOSE_SITTING":496,"AIRBENDER_CHARGING":757,"VACUUM_GHOST_CAPTURED":58,"AXOLOTL_IDLE":60,"WARLOCK_WALK":504,"INFERNO_SWORD_CHARGE":165,"PIRATE_PENGUIN_FALL":109,"FISHING_ROD_IDLE":74,"ANUBIS_IDLE":775,"FP_LASSO_CHARGE":23,"CAPTAIN_PENGUIN_ATTACK_2":111,"CRAB_WALK_RIGHT":642,"BOW_AIM":128,"SPIDER_ATTACK":500,"SCYTHE_PULL_1_FP":428,"SLIME_IDLE":520,"FIRE_SHEEP_SPAWN":380,"CLASSIC_PENGUIN_JUMP":216,"EGYPTIAN_CAT_BLINK":761,"CLASSIC_WIZARD_PENGUIN_WALK":220,"GOLDEN_GOOSE_FLY":491,"TRIUMPH_STATUE_1":659,"VOID_DRAGON_GLIDE":257,"FP_PAINT_SHOTGUN_IDLE":137,"TARGET_DUMMY_SPIN_ATTACK":545,"PENGUIN_WALK_2":207,"EQUIP_2":9,"DAGGER_SWING_2_FP":419,"TURTLE_BLINK":637,"GREAT_HAMMER_CHARGE_FP":437,"DUST_DEVIL_PLAYER":768,"CRAB_BOSS_CLAW_ATTACK":478,"VOID_CRAB_DEATH":197,"JUGGERNAUT_POSE":322,"SHIELD_SWORD_WALKING_FP":474,"NORMAL_PENGUIN_JUMP":100,"DEVOUR_ACTION":468,"CLIMB_ROPE":282,"SPEAR_THROW":81,"EGG_HUNT_PLAYER_DANCE":586,"CONDIMENT_GUN_FP":469,"PAN_CHARGE":157,"DRAGON_SLAYER_LAUNCH_LOOP":254,"SEAHORSE_BEAM":365,"HALLOWEEN_ALTAR_JUMP":298,"SUCKED_INTO_HOLE":514,"SCISSOR_SWORD_COMBO_STRIKE":568,"SPIDER_WALK":501,"MEDITATE":371,"GOLEM_BOSS_IDLE":387,"DUCK_WALK":115,"DUCK_IDLE":116,"CHICKEN_ATTACK":462,"PIRATE_SHIP_FLY":236,"BIG_PENGUIN_IDLE":106,"HANG_GLIDER_ARM":87,"DRAGON_SMASH_2":562,"BROOM_SWEEP":457,"GIANT_GLOVE_FLICK":456,"SKORP_IDLE":786,"BOXING_GLOVE_UPPER_CUT":455,"CHEST_OPEN":96,"VOID_GOLEM_PORTAL_ATTACK":393,"REBELLION_WAVE_FLAG":667,"FROSTY_SHIELD_SUMMON":346,"WINTER_BOSS_SPIN":360,"GUITAR_PLAY":20,"DEFAULT_SPIDER_BITE":684,"SEAHORSE_SPAWN":368,"GOLEM_BOSS_MOVE":388,"GAUNTLETS_HOOK_1ST":447,"GREAT_HAMMER_CHARGE":433,"DINO_JUMP":176,"SPIDER_QUEEN_FLY_UP":703,"FP_TWIRLBLADE_ATTACK_1":125,"KICK_5":530,"VOID_DRAGON_WINGS_FLAP":256,"DRAGON_GLIDING":252,"CRAB_BLINK":643,"GAUNTLETS_SUPER_PUNCH":442,"PENGUIN_PIRATE_SHIP_FLY":237,"SMOKE_JUMP_DOWN":242,"GREAT_HAMMER_SWING_1_FP":434,"GREAT_HAMMER_SWING_1":430,"VOID_CRAB_ATTACKED":196,"OPEN_CRATE":120,"SPRAY":29,"TALL_PENGUIN_IDLE":102,"JADE_HAMMER_SLAM":40,"FLYING_LUCKY_BLOCK_FLAP":414,"FP_HANDS_RUNNING_LEFT_ARM":308,"FLYING_BACKPACK_FLAP":413,"CRAB_BOSS_STAB_230":488,"SHIELD_SWORD_IDLE_FP":475,"FP_CROSSBOW_FIRE":17,"JUGGERNAUT_LEAP_ATTACK":318,"INFERNAL_SHIELD_SLAM":403,"SNAP_TRAP_SETUP":70,"DODO_BIRD_JUMP":45,"BREAK_BLOCK":623,"MERCHANT_PURCHASE":408,"GLUE_TRAP_CHARGING_IDLE":316,"OWL_HEAL":376,"KIT_MASTERY_EMOTE":576,"COMET_VOLLEY_COMET_FIRED":554,"GOLEM_BOSS_DEATH":392,"DINO_CHARGING":178,"CRYSTAL_GROW":467,"FP_HEAVENLY_SWORD_CHARGE":172,"TAKE_SELFIE":725,"GAUNTLETS_JAB_1ST":445,"AXOLOTL_REINDEER_ABILITY":66,"NINJA_THROW_CHAKRAM_SHORTENED":534,"HEAVENLY_SWORD_CHARGE":167,"VOID_PORTAL_EXCITED":205,"OWL_FLY":374,"VOID_DRAGON_BREATH":259,"CLASSIC_PENGUIN_ATTACK":213,"VOID_CRAB_LEFT_ATTACK":194,"HEADHUNTER_AIM_FP":412,"CAPTAIN_PENGUIN_ABILITY":112,"DAO_DASH":114,"ELK_UPPERCUT":185,"FROSTY_HAMMER_3":349,"MELODY_ROCKSTAR_AD":158,"VOID_CRAB_EYE_MOVEMENT":198,"FIRE_SHEEP_CHARGE":379,"SUMMONER_CHARACTER_SWIPE":670,"AXOLOTL_REINDEER_IDLE":64,"BLACKHOLE_CONSUME":249,"NEW_SWORD_SWING_FP":773,"WARRIOR_SPIDER_WALK":701,"SCYTHE_HOLD":429,"LASER_SWORD_SWING_2":341,"SCISSOR_SWORD_SWING_2":570,"HOVER_BOARD_TRICK":302,"CRAB_DANCE":646,"JUGGERNAUT_ULTIMATE":332,"KAZOTSKY_KICK":454,"HOVER_BOARD_MOVE":301,"JUGGERNAUT_SWING":321,"SPEAR_STAB_1":673,"KEEPER_WALK":279,"GHOST_SPIN":80,"VOID_CRAB_BEAM_ATTACK":192,"DODO_BIRD_IDLE":43,"EASTER_BUNNY_EMOTE_PLAYER":162,"FP_HOLD_SWORD":12,"SEAHORSE_SHOOT":367,"PENGUIN_IDLE_2":208,"VOID_HOUND_JUMP":736,"BOBA_BLASTER_IDLE":152,"SCYTHE_IDLE":92}}